[
    {
        "id": "cama1",
        "nombre": "cama",
        "stock": 3,
        "precio": 50000,
        "imagen": "cama.jpg"
    },
    {
        "id": "cama2",
        "nombre": "cama",
        "stock": 5,
        "precio": 60000,
        "imagen": "cama2.jpg"
    },
    {
        "id": "cama3",
        "nombre": "cama",
        "stock": 10,
        "precio": 40000,
        "imagen": "cama3.jpg"
    },
    {
        "id": "collar1",
        "nombre": "collar",
        "stock": 9,
        "precio": 30000,
        "imagen": "collar-corbatin.jpg"
    },
    {
        "id": "collar2",
        "nombre": "collar",
        "stock": 8,
        "precio": 60000,
        "imagen": "collar-rojo.jpeg"
    },
    {
        "id": "comedero1",
        "nombre": "comedero",
        "stock": 7,
        "precio": 90000,
        "imagen": "comedero1.jpg"
    },
    {
        "id": "comedero2",
        "nombre": "comedero",
        "stock": 5,
        "precio": 70000,
        "imagen": "comedero2.jpg"
    },
    {
        "id": "comedero3",
        "nombre": "comedero",
        "stock": 7,
        "precio": 100000,
        "imagen": "comedero3.jpg"
    },
    {
        "id": "aro",
        "nombre": "juguete",
        "stock": 7,
        "precio": 30000,
        "imagen": "juguete-aro.jpg"
    },
    {
        "id": "hueso",
        "nombre": "juguete",
        "stock": 8,
        "precio": 20000,
        "imagen": "juguete-hueso.jpg"
    },
    {
        "id": "pelota",
        "nombre": "juguete",
        "stock": 6,
        "precio": 30000,
        "imagen": "juguete-pelota.jpg"
    },
    {
        "id": "kit1",
        "nombre": "Kit perro",
        "stock": 4,
        "precio": 150000,
        "imagen": "kit1.jpg"
    },
    {
        "id": "kit2",
        "nombre": "Kit perro",
        "stock": 3,
        "precio": 120000,
        "imagen": "kit2.jpg"
    },
    {
        "id": "kit3",
        "nombre": "Kit perro",
        "stock": 6,
        "precio": 110000,
        "imagen": "kit3.jpg"
    }
]